README.md
ewn.conf
setup.cfg
setup.py
ewn/__init__.py
ewn.egg-info/PKG-INFO
ewn.egg-info/SOURCES.txt
ewn.egg-info/dependency_links.txt
ewn.egg-info/entry_points.txt
ewn.egg-info/requires.txt
ewn.egg-info/top_level.txt