Metadata-Version: 1.1
Name: ewn
Version: 1.0.9
Summary: Execute With Notify
Home-page: https://github.com/larrabee/ewn
Author: larrabee
Author-email: kafatron@gmail.com
License: GPLv3
Keywords: ewn wrapper
Platform: UNKNOWN
Classifier: Development Status :: 5 - Production/Stable
Classifier: Environment :: Console
Classifier: Intended Audience :: System Administrators
Classifier: Topic :: System :: Logging
Classifier: Topic :: Utilities
Classifier: License :: OSI Approved :: GNU General Public License v3 (GPLv3)
Classifier: Programming Language :: Python :: 2 :: Only
Classifier: Programming Language :: Python :: 2.7
